setup.cfg
setup.py
ezrpy/__init__.py
ezrpy/core.py
ezrpy/db.py
ezrpy/error.py
ezrpy/handle.py
ezrpy/route.py
ezrpy/utils.py
ezrpy.egg-info/PKG-INFO
ezrpy.egg-info/SOURCES.txt
ezrpy.egg-info/dependency_links.txt
ezrpy.egg-info/requires.txt
ezrpy.egg-info/top_level.txt
scripts/ezt