Metadata-Version: 1.0
Name: ezrpy
Version: 0.1.7
Summary: Automatic REST API for Prototypes
Home-page: https://github.com/mijara/ezrpy
Author: Marcelo Jara
Author-email: marjara35@gmail.com
License: UNKNOWN
Keywords: rest,prototype,api
Platform: UNKNOWN
